atesa/__init__.py
atesa/_version.py
atesa/auto_cvs.py
atesa/batchsystem.py
atesa/boltzmann_weight.py
atesa/configure.py
atesa/factory.py
atesa/information_error.py
atesa/interpret.py
atesa/jobtype.py
atesa/lmax.py
atesa/main.py
atesa/mbar.py
atesa/mdengine.py
atesa/process.py
atesa/rc_eval.py
atesa/resample_and_inferr.py
atesa/resampling.py
atesa/taskmanager.py
atesa/utilities.py
atesa/data/README.md
atesa/data/atesa.config
atesa/data/input_files/aimless_shooting_init_amber.in
atesa/data/input_files/aimless_shooting_init_cp2k.in
atesa/data/input_files/aimless_shooting_prod_amber.in
atesa/data/input_files/aimless_shooting_prod_cp2k.in
atesa/data/input_files/committor_analysis_prod_amber.in
atesa/data/input_files/committor_analysis_prod_cp2k.in
atesa/data/input_files/equilibrium_path_sampling_init_amber.in
atesa/data/input_files/equilibrium_path_sampling_init_cp2k.in
atesa/data/input_files/equilibrium_path_sampling_prod_amber.in
atesa/data/input_files/equilibrium_path_sampling_prod_cp2k.in
atesa/data/input_files/find_ts_prod_amber.in
atesa/data/input_files/find_ts_prod_cp2k.in
atesa/data/input_files/umbrella_sampling_prod_amber.in
atesa/data/input_files/umbrella_sampling_prod_cp2k.in
atesa/data/templates/amber_pbs.tpl
atesa/data/templates/amber_slurm.tpl
atesa/data/templates/cp2k_slurm.tpl
atesa/tests/__init__.py
atesa/tests/temp.config
atesa/tests/test_auto_cvs.py
atesa/tests/test_boltzmann_weight.py
atesa/tests/test_information_error.py
atesa/tests/test_jobtype.py
atesa/tests/test_lmax.py
atesa/tests/test_main.py
atesa/tests/test_mbar.py
atesa/tests/test_mdengine.py
atesa/tests/test_process.py
atesa/tests/test_rc_eval.py
atesa/tests/test_resampling.py
atesa/tests/test_utilities.py
atesa/tests/test_data/1.1_1.2_2.2_2.6.rst7_2_10_init_fwd.rst_2_1_2.rst7_5_init_fwd.rst
atesa/tests/test_data/1.1_1.2_2.2_2.6.rst7_2_10_init_fwd.rst_4_58_3.rst7_4_init_fwd.rst
atesa/tests/test_data/as.out
atesa/tests/test_data/as_big.out
atesa/tests/test_data/as_big_123.out
atesa-1.0.2.dist-info/._PKG-INFO
atesa-1.0.2.dist-info/._SOURCES.txt
atesa-1.0.2.dist-info/._dependency_links.txt
atesa-1.0.2.dist-info/._entry_points.txt
atesa-1.0.2.dist-info/._requires.txt
atesa-1.0.2.dist-info/._top_level.txt
atesa-1.0.2.dist-info/LICENSE
atesa-1.0.2.dist-info/METADATA
atesa-1.0.2.dist-info/WHEEL
atesa-1.0.2.dist-info/entry_points.txt
atesa-1.0.2.dist-info/top_level.txt
atesa-1.0.2.dist-info/RECORD
