Metadata-Version: 2.1
Name: atesa
Version: 1.0.2
Home-page: https://atesa.readthedocs.io/en/latest/
Author: Tucker Burgin
Author-email: tburgin@umich.edu
License: BSD-3-Clause
Requires-Python: >=3.5, <3.12
License-File: LICENSE
Requires-Dist: pytraj >=2.0
Requires-Dist: numpy
Requires-Dist: mdtraj
Requires-Dist: django
Requires-Dist: statsmodels
Requires-Dist: oslo.concurrency
Requires-Dist: multiprocess
Requires-Dist: pydantic
Requires-Dist: gnuplotlib
Requires-Dist: numdifftools
Requires-Dist: matplotlib <3.8
Requires-Dist: psutil
Requires-Dist: pymbar <4.0
